{
   "ssoCheckUrl": null,
   "status":"success",
   "message":null,
   "param":{},
   "data": [
      {
         "agNum": 893,
         "agMc":"전문점유통담당",
         "agCode":"A965",
         "agOrgCode":"A965",
         "agName":"논현역점",
         "agTel":"02-517-7447",
         "agDetailPage": null,
         "agFax":"02-517-3993",
         "agEmail":"KR013419001B@lgesalespartner.com",
         "agZipcode":"06044",
         "agAddr1":"서울특별시 강남구 논현동 50-3 스카이저축은행",
         "agAddr2":"LG 베스트샵 논현역점",
         "agChiefEmail":"KR013419001B@lgesalespartner.com",
         "agWeekday":"09:30~21:00",
         "agSaturday":"09:30~21:00",
         "agRegdate":"20150325",
         "agGpsX":"37.51152253100276",
         "agGpsY":"127.02182060306917",
         "distance": 0.7,
         "agNZipcode": null,
         "agNAddr1":"서울특별시 강남구 학동로 103(논현동)",
         "agNAddr2":"LG 베스트샵 논현역점",
         "agSunday":"09:30~21:00",
         "agHoliday":"1",
         "agHolidayEtc":"설날,추석 당일 휴무",
         "agChiefName":"서흥석",
         "agChiefPhone":"010-2203-7777",
         "agClass":"CLASS002",
         "agCh":"002",
         "agCenterWeekday":"09:00 ~ 18:00",
         "agCenterSaturday":"09:00 ~ 13:00",
         "agCenterHoilday":"휴무",
         "agCenterType":"0",
         "agContent":"LG전자 BEST SHOP을 찾아주셔서 감사합니다. 친철하고 편안하게 모시겠습니다. 감사합니다",
         "agNewShopComment": null,
         "agProduct":"TV, PC, 모니터, 냉장고, 김치냉장고, 세탁기, 건조기, 스타일러, 에어컨, 공기청정기, 제습기, 가습기, 정수기, 청소기, 전자레인지, 전기레인지, 안마의자, 소형가전, 프라엘, 모바일",
         "car":"정보 업데이트 예정입니다.",
         "subway":"7호선 논현역 8번출구 학동역방향 하나은행바로옆건물",
         "guide":"매장 후면 주차가능",
         "bus":"정보 업데이트 예정입니다.",
         "mobileFlag":"Y",
         "agWeekendOff":"Y",
         "agCounsel":"Y",
         "browngoodsFlag":"Y",
         "evtSmartworld": null,
         "evtZin": null,
         "evtBeermaker": null,
         "shopPhote":"893_1.jpg, 893_2.jpg, 893_3.jpg",
         "cFilePath":"/uploads/front/bestshop/admin/shopInfo/",
         "cFileGubun":"BESTPC"
      }, 
      {
         "agNum": 4125,
         "agMc":"하이프라자",
         "agCode":"1292",
         "agOrgCode":"1292",
         "agName":"강남본점",
         "agTel":"02-3448-5191",
         "agDetailPage": null,
         "agFax":"02-3448-5190",
         "agEmail":"prince@hiplaza.co.kr",
         "agZipcode":"06014",
         "agAddr1":"서울특별시 강남구 청담동 86-1 LG 청담빌딩",
         "agAddr2":"LG BEST SHOP",
         "agChiefEmail":"prince@hiplaza.co.kr",
         "agWeekday":"10:30~20:30",
         "agSaturday":"10:30~20:30",
         "agRegdate":"20150529",
         "agGpsX":"37.5235644",
         "agGpsY":"127.0395764",
         "distance": 1.7,
         "agNZipcode": null,
         "agNAddr1":"서울특별시 강남구 도산대로 403(청담동)",
         "agNAddr2":"LG BEST SHOP",
         "agSunday":"11:00~20:30",
         "agHoliday":"1",
         "agHolidayEtc": null,
         "agChiefName":"윤정훈",
         "agChiefPhone":"010-2012-3313",
         "agClass":"CLASS001",
         "agCh":"001",
         "agCenterWeekday":"09:00 ~ 18:00",
         "agCenterSaturday":"09:00 ~ 13:00",
         "agCenterHoilday":"휴무",
         "agCenterType":"3",
         "agContent":"LG전자 BEST SHOP을 찾아주셔서 감사합니다. 친철하고 편안하게 모시겠습니다. 감사합니다",
         "agNewShopComment":"시그니처 전용관 오픈",
         "agProduct":"TV, 냉장고, 세탁기, 에어컨, 건조기, 전기레인지, 식기세척기, 맥주제조기, 스타일러, 공기청정기, 청소기, 프라엘, 김치냉장고, PC, 모니터, 광파오븐, 전자레인지, 제습기, 안마의자, LG 오브제, LG 시그니처, 휴대폰, 소형가전",
         "car":"영동대교 남단 방향에서 도산대로 방향 우회전→청담사거리 직진 →학동사거리(학동역 사거리 와는 틀림) 건너기 전 우측 코너에 위치",
         "subway":"7호선 강남구청역 4번 출구에서 학동사거리 방향 700미터 학동사거리 횡단보도 건너 위치, 분당선 압구정로데오역 4번 출구에서 학동사거리 방향 350미터 위치",
         "guide":"강남본점 건물 22대 주차 가능합니다",
         "bus":"강남구청역 방향에서 4412/301 승차 일지아트홀 정류장(학동사거리) 하차, \r\n압구정동 방향에서 2411/143승차 영동고교앞 정류장하차 학동사거리 200미터 도보, \r\n신사동 방향에서 4212/145/4412 승차 호림아트홀 정류장 하차 학동사거리 150미터 도보, \r\n영동대교 방향에서 4212 승차 호림아트홀 하차 학동사거리 150미터 도보",
         "mobileFlag":"Y",
         "agWeekendOff":"Y",
         "agCounsel":"Y",
         "browngoodsFlag":"Y",
         "evtSmartworld":"Y",
         "evtZin":"Y",
         "evtBeermaker":"Y",
         "shopPhote":"20200311104553092.jpg, 20200311104553110.jpg, 20200311104553111.jpg",
         "cFilePath":"/uploads/front/bestshop/admin/shopInfo/",
         "cFileGubun":"BESTPC"
      }, 
      {
         "agNum": 5647,
         "agMc":"하이프라자",
         "agCode":"0967",
         "agOrgCode":"0967",
         "agName":"현대 본점",
         "agTel":"02-3444-9057",
         "agDetailPage": null,
         "agFax": null,
         "agEmail":"kimson0929@hiplaza.co.kr",
         "agZipcode":"06001",
         "agAddr1":"서울특별시 강남구 압구정동 429",
         "agAddr2":"지하 1층",
         "agChiefEmail":"kimson0929@hiplaza.co.kr",
         "agWeekday":"10:30-20:00",
         "agSaturday":"10:30-20:30",
         "agRegdate":"20180770",
         "agGpsX":"37.527342",
         "agGpsY":"127.027561",
         "distance": 1.8,
         "agNZipcode": null,
         "agNAddr1":"서울특별시 강남구 압구정로 165",
         "agNAddr2":"지하 1층",
         "agSunday":"10:30-20:30",
         "agHoliday": null,
         "agHolidayEtc":"지점 정기휴무일은 백화점 홈페이지를 통해 확인가능",
         "agChiefName":"김진욱",
         "agChiefPhone":"010-9181-0000",
         "agClass":"CLASS011",
         "agCh":"011",
         "agCenterWeekday": null,
         "agCenterSaturday": null,
         "agCenterHoilday": null,
         "agCenterType":"0",
         "agContent":"안녕하세요. 오늘도 저희 지점을 찾아주셔서 감사합니다. 즐거운 쇼핑하시기 바랍니다!",
         "agNewShopComment": null,
         "agProduct":"TV, 냉장고, 세탁기, 에어컨, 건조기, 전기레인지, 식기세척기, 맥주제조기, 스타일러, 공기청정기, 청소기, 프라엘, 김치냉장고, PC, 모니터, 광파오븐, 전자레인지, 제습기, 안마의자, LG 오브제, LG 시그니처, 휴대폰(자급제)",
         "car":"네이게이션에서 \"지점명\"을 검색해주세요",
         "subway":"압구정역(3호선)6번출구",
         "guide":"백화점 내 주차가능",
         "bus":"6006,143,148,240,301,351,362,440,472,2411,3011,4318,4412,4419,9407,9507,240,147",
         "mobileFlag":"N",
         "agWeekendOff":"Y",
         "agCounsel":"Y",
         "browngoodsFlag":"N",
         "evtSmartworld": null,
         "evtZin": null,
         "evtBeermaker": null,
         "shopPhote":"5647_1.jpg, 5647_2.jpg, 5647_3.jpg",
         "cFilePath":"/uploads/front/bestshop/admin/shopInfo/",
         "cFileGubun":"BESTPC"
      },
      {
         "agNum": 5637,
         "agMc":"하이프라자",
         "agCode":"2254",
         "agOrgCode":"2254",
         "agName":"갤러리아 명품관 WEST점",
         "agTel":"02-541-5842",
         "agDetailPage": null,
         "agFax": null,
         "agEmail":"ki1002@hiplaza.co.kr",
         "agZipcode":"06008",
         "agAddr1":"서울특별시 강남구 압구정동 494",
         "agAddr2":"5층",
         "agChiefEmail":"ki1002@hiplaza.co.kr",
         "agWeekday":"10:30-20:00",
         "agSaturday":"10:30-20:30",
         "agRegdate":"20180760",
         "agGpsX":"37.528492",
         "agGpsY":"127.039922",
         "distance": 2.2,
         "agNZipcode": null,
         "agNAddr1":"서울특별시 강남구 압구정로 343",
         "agNAddr2":"5층",
         "agSunday":"10:30-20:30",
         "agHoliday": null,
         "agHolidayEtc":"지점 정기휴무일은 백화점 홈페이지를 통해 확인가능",
         "agChiefName":"윤기천",
         "agChiefPhone":"010-3669-6789",
         "agClass":"CLASS011",
         "agCh":"011",
         "agCenterWeekday": null,
         "agCenterSaturday": null,
         "agCenterHoilday": null,
         "agCenterType":"0",
         "agContent":"안녕하세요. 오늘도 저희 지점을 찾아주셔서 감사합니다. 즐거운 쇼핑하시기 바랍니다!",
         "agNewShopComment": null,
         "agProduct":"TV, 냉장고, 세탁기, 에어컨, 건조기, 전기레인지, 식기세척기, 맥주제조기, 스타일러, 공기청정기, 청소기, 프라엘, 김치냉장고, PC, 모니터, 광파오븐, 전자레인지, 제습기, 안마의자, LG 오브제, LG 시그니처, 휴대폰(자급제)",
         "car":"네이게이션에서 \"지점명\"을 검색해주세요",
         "subway":"압구정로데오역(분당선)",
         "guide":"백화점 내 주차가능",
         "bus":"143,145,240,301,351,362,440,472,2411,4318,4412,4419,6006",
         "mobileFlag":"N",
         "agWeekendOff":"Y",
         "agCounsel":"Y",
         "browngoodsFlag":"N",
         "evtSmartworld": null,
         "evtZin": null,
         "evtBeermaker": null,
         "shopPhote":"5637_1.jpg, 5637_3.jpg, 5637_2.jpg",
         "cFilePath":"/uploads/front/bestshop/admin/shopInfo/",
         "cFileGubun":"BESTPC"
      }, 
      {
         "agNum": 5622,
         "agMc":"하이프라자",
         "agCode":"0945",
         "agOrgCode":"0945",
         "agName":"신세계 강남점",
         "agTel":"02-3479-6271",
         "agDetailPage": null,
         "agFax": null,
         "agEmail":"dotori0918@hiplaza.co.kr",
         "agZipcode":"06546",
         "agAddr1":"서울특별시 서초구 반포동 19-3 센트럴시티",
         "agAddr2":"9층 LG전자 베스트샵 신세계 강남점",
         "agChiefEmail":"dotori0918@hiplaza.co.kr",
         "agWeekday":"10:30-20:00",
         "agSaturday":"10:30-20:30",
         "agRegdate":"20180745",
         "agGpsX":"37.5049608",
         "agGpsY":"127.004237",
         "distance": 2.3,
         "agNZipcode": null,
         "agNAddr1":"서울특별시 서초구 신반포로 176(반포동)",
         "agNAddr2":"9층 LG전자 베스트샵 신세계 강남점",
         "agSunday":"10:30-20:30",
         "agHoliday": null,
         "agHolidayEtc":"지점 정기휴무일은 백화점 홈페이지를 통해 확인가능",
         "agChiefName":"정소영",
         "agChiefPhone":"010-4127-8493",
         "agClass":"CLASS011",
         "agCh":"011",
         "agCenterWeekday": null,
         "agCenterSaturday": null,
         "agCenterHoilday": null,
         "agCenterType":"0",
         "agContent":"안녕하세요. 오늘도 저희 지점을 찾아주셔서 감사합니다. 즐거운 쇼핑하시기 바랍니다!",
         "agNewShopComment": null,
         "agProduct":"TV, 냉장고, 세탁기, 에어컨, 건조기, 전기레인지, 식기세척기, 맥주제조기, 스타일러, 공기청정기, 청소기, 프라엘, 김치냉장고, PC, 모니터, 광파오븐, 전자레인지, 제습기, 안마의자, LG 오브제, LG 시그니처, 휴대폰(자급제)",
         "car":"네이게이션에서 \"지점명\"을 검색해주세요",
         "subway":"3, 7, 9호선 고속버스터미널역",
         "guide":"백화점 내 주차가능",
         "bus":"3414, 3420, 3423, 4212, 4318, 4425, 6411, 143, 148, 360, 362, 401, 462, 540, 640, 642, 643, 9408, 5413, 412, 8401, 8451",
         "mobileFlag":"N",
         "agWeekendOff":"Y",
         "agCounsel":"Y",
         "browngoodsFlag":"N",
         "evtSmartworld": null,
         "evtZin": null,
         "evtBeermaker": null,
         "shopPhote":"5622_2.jpg, 5622_3.jpg, 5622_1.jpg",
         "cFilePath":"/uploads/front/bestshop/admin/shopInfo/",
         "cFileGubun":"BESTPC"
      }, 
      {
         "agNum": 3065,
         "agMc":"하이프라자",
         "agCode":"1037",
         "agOrgCode":"1037",
         "agName":"반포점",
         "agTel":"02-592-4343",
         "agDetailPage": null,
         "agFax":"02-592-5494",
         "agEmail":"ester32@hiplaza.co.kr",
         "agZipcode":"06512",
         "agAddr1":"서울특별시 서초구 잠원동 75-13 반포쇼핑타운",
         "agAddr2":"반포쇼핑타운 2동 1층 LG BEST SHOP",
         "agChiefEmail":"ester32@hiplaza.co.kr",
         "agWeekday":"10:30~20:30",
         "agSaturday":"10:30~20:30",
         "agRegdate":"20150114",
         "agGpsX":"37.5056944",
         "agGpsY":"127.0023219",
         "distance": 2.4,
         "agNZipcode": null,
         "agNAddr1":"서울특별시 서초구 신반포로 165(잠원동)",
         "agNAddr2":"반포쇼핑타운 2동 1층 LG BEST SHOP",
         "agSunday":"11:00~20:30",
         "agHoliday":"1",
         "agHolidayEtc": null,
         "agChiefName":"임상두",
         "agChiefPhone":"010-8941-5813",
         "agClass":"CLASS001",
         "agCh":"001",
         "agCenterWeekday":"09:00 ~ 18:00",
         "agCenterSaturday":"09:00 ~ 13:00",
         "agCenterHoilday":"휴무",
         "agCenterType":"1",
         "agContent":"LG전자 BEST SHOP을 찾아주셔서 감사합니다. 친철하고 편안하게 모시겠습니다. 감사합니다",
         "agNewShopComment": null,
         "agProduct":"TV, 냉장고, 세탁기, 에어컨, 건조기, 전기레인지, 식기세척기, 맥주제조기, 스타일러, 공기청정기, 청소기, 프라엘, 김치냉장고, PC, 모니터, 광파오븐, 전자레인지, 제습기, 안마의자, LG 오브제, LG 시그니처, 휴대폰, 소형가전",
         "car":"신세계 강남점 맞은편 반포종합상가 2동\r\n고속버스터미널 맞은편 반포고가차도 방면 300m",
         "subway":"9호선 고속버스터미널역 8-1번 출구 방향 50m\r\n3호선, 7호선 고속버스터미널역",
         "guide":"매장 건물 뒷편 100대 사용가능",
         "bus":"간선(B)142,143,148,342,360,362,401,406,462,540,640,642,643,8401,8541\r\n지선(G)3414,3422,3423,4212,4318,4425,5413,6411\r\n광역(B)9408,9500,9501,9800,9801,9900\r\n마을(마)서초10, 서초13, 서초14, 서초21\r\n좌석(좌)1500-3\r\n공항(공)6000, 6020, 6040",
         "mobileFlag":"Y",
         "agWeekendOff":"Y",
         "agCounsel":"Y",
         "browngoodsFlag":"Y",
         "evtSmartworld":"Y",
         "evtZin": null,
         "evtBeermaker": null,
         "shopPhote":"3065_1.jpg, 3065_2.jpg, 3065_3.jpg",
         "cFilePath":"/uploads/front/bestshop/admin/shopInfo/",
         "cFileGubun":"BESTPC"
      }, 
      {
         "agNum": 3470,
         "agMc":"하이프라자",
         "agCode":"1117",
         "agOrgCode":"1117",
         "agName":"서초점",
         "agTel":"02-584-6868",
         "agDetailPage": null,
         "agFax":"02-584-0830",
         "agEmail":"nanjibin@hiplaza.co.kr",
         "agZipcode":"06727",
         "agAddr1":"서울특별시 서초구 서초동 1342-4 LG전자대리점",
         "agAddr2":"LG전자 베스트샵 서초점",
         "agChiefEmail":"nanjibin@hiplaza.co.kr",
         "agWeekday":"10:30~20:30",
         "agSaturday":"10:30~20:30",
         "agRegdate":"20160331",
         "agGpsX":"37.4881898",
         "agGpsY":"127.028056",
         "distance": 2.5,
         "agNZipcode": null,
         "agNAddr1":"서울특별시 서초구 효령로 406(서초동)",
         "agNAddr2":"LG전자 베스트샵 서초점",
         "agSunday":"11:00~20:30",
         "agHoliday":"1",
         "agHolidayEtc": null,
         "agChiefName":"정지빈",
         "agChiefPhone":"010-7378-9987",
         "agClass":"CLASS001",
         "agCh":"001",
         "agCenterWeekday":"09:00 ~ 18:00",
         "agCenterSaturday":"09:00 ~ 13:00",
         "agCenterHoilday":"휴무",
         "agCenterType":"0",
         "agContent":"LG전자 BEST SHOP을 찾아주셔서 감사합니다. 친철하고 편안하게 모시겠습니다. 감사합니다",
         "agNewShopComment": null,
         "agProduct":"TV, 냉장고, 세탁기, 에어컨, 건조기, 전기레인지, 식기세척기, 맥주제조기, 스타일러, 공기청정기, 청소기, 프라엘, 김치냉장고, PC, 모니터, 광파오븐, 전자레인지, 제습기, 안마의자, LG 오브제, LG 시그니처, 휴대폰, 소형가전",
         "car":"내비게이션 : 서초구 서초동 1342-4",
         "subway":"3호선 양재역 1번 출구 655m\r\n3호선 남부터미널 3번 출구 약 1.5 Km",
         "guide":"건물 앞면 3~4대 주차가능",
         "bus":"일반버스 : 461,641,3423,4319,11 [무지개 아파트 하차]\r\n마을버스 : 11, 21 [무지개 아파트 후문]",
         "mobileFlag":"Y",
         "agWeekendOff":"Y",
         "agCounsel":"Y",
         "browngoodsFlag":"Y",
         "evtSmartworld": null,
         "evtZin": null,
         "evtBeermaker": null,
         "shopPhote":"3470_1.jpg, 3470_2.jpg, 3470_3.jpg",
         "cFilePath":"/uploads/front/bestshop/admin/shopInfo/",
         "cFileGubun":"BESTPC"
      }, 
      {
         "agNum": 5639,
         "agMc":"하이프라자",
         "agCode":"0895",
         "agOrgCode":"0895",
         "agName":"롯데 강남점",
         "agTel":"02-531-2809",
         "agDetailPage": null,
         "agFax": null,
         "agEmail":"tjddnd3680@hiplaza.co.kr",
         "agZipcode":"06206",
         "agAddr1":"서울특별시 강남구 대치동 937",
         "agAddr2":"8층",
         "agChiefEmail":"tjddnd3680@hiplaza.co.kr",
         "agWeekday":"10:30-20:00",
         "agSaturday":"10:30-20:30",
         "agRegdate":"20180762",
         "agGpsX":"37.496993",
         "agGpsY":"127.053162",
         "distance": 2.6,
         "agNZipcode": null,
         "agNAddr1":"서울특별시 강남구 도곡로 401",
         "agNAddr2":"8층",
         "agSunday":"10:30-20:30",
         "agHoliday": null,
         "agHolidayEtc":"지점 정기휴무일은 백화점 홈페이지를 통해 확인가능",
         "agChiefName":"최성웅",
         "agChiefPhone":"010-9048-3680",
         "agClass":"CLASS011",
         "agCh":"011",
         "agCenterWeekday": null,
         "agCenterSaturday": null,
         "agCenterHoilday": null,
         "agCenterType":"0",
         "agContent":"안녕하세요. 오늘도 저희 지점을 찾아주셔서 감사합니다. 즐거운 쇼핑하시기 바랍니다!",
         "agNewShopComment": null,
         "agProduct":"TV, 냉장고, 세탁기, 에어컨, 건조기, 전기레인지, 식기세척기, 맥주제조기, 스타일러, 공기청정기, 청소기, 프라엘, 김치냉장고, PC, 모니터, 광파오븐, 전자레인지, 제습기, 안마의자, LG 오브제, LG 시그니처, 휴대폰(자급제)",
         "car":"네이게이션에서 \"지점명\"을 검색해주세요",
         "subway":"지하철 분당선 한티역",
         "guide":"백화점 내 주차가능",
         "bus":"333, 340, 420, 461, 4412, 242, 333, 472, 3422, 3426, 4412, 6411, 9414",
         "mobileFlag":"N",
         "agWeekendOff":"Y",
         "agCounsel":"Y",
         "browngoodsFlag":"N",
         "evtSmartworld": null,
         "evtZin": null,
         "evtBeermaker": null,
         "shopPhote":"5639_1.jpg, 5639_3.jpg, 5639_2.jpg",
         "cFilePath":"/uploads/front/bestshop/admin/shopInfo/",
         "cFileGubun":"BESTPC"
      }
   ]
}