{
    "status":"success",
    "message":null,
    "param":{
        "pagination":{
            "page":"3",
            "visibleCount":"7",
            "totalCount":"23"
        }
    },
    "data": {
        "totalCount":"63",
        "listData":[
            {
                "title":"[프로그램/Win7_32bit] XPION용 LG intelligent Update 프로그램 1",
                "version":"ver 7.7PHV1 데스크톱/일체형",
                "category":"통합 드라이버 설치 프로그램",
                "date":"20190101",
                "url":"https://www.lgservice.co.kr/fileExDownload.do?filePath=/data001/GSCS/FILE/P1/file/2018/01/2018-01-24&fileName=c0a8ed6e03324c96887cf6a649fbb020.pdf&fileRealName=MFL67233150_171127.pdf&check=true",
                "fileSize":"118.1MB",
                "list":[
                    {
                        "title":"[프로그램/Win7_32bit] XPION용 LG intelligent Update 프로그램 2",
                        "version":"ver 7.7PHV2 데스크톱/일체형",
                        "category":"통합 드라이버 설치 프로그램",
                        "date":"20190102",
                        "url":"https://www.lgservice.co.kr/fileExDownload.do?filePath=/data001/GSCS/FILE/P1/file/2018/01/2018-01-24&fileName=c0a8ed6e03324c96887cf6a649fbb020.pdf&fileRealName=MFL67233150_171127.pdf&check=true",
                        "fileSize":"118.2MB"
                    },
                    {
                        "title":"[프로그램/Win7_32bit] XPION용 LG intelligent Update 프로그램 3",
                        "version":"ver 7.7PHV3 데스크톱/일체형",
                        "category":"통합 드라이버 설치 프로그램",
                        "date":"20190103",
                        "url":"https://www.lgservice.co.kr/fileExDownload.do?filePath=/data001/GSCS/FILE/P1/file/2018/01/2018-01-24&fileName=c0a8ed6e03324c96887cf6a649fbb020.pdf&fileRealName=MFL67233150_171127.pdf&check=true",
                        "fileSize":"118.3MB"
                    }
                ]
            },
            {
                "title":"[프로그램/Win7_32bit] XPION용 LG intelligent Update 프로그램 4",
                "version":"ver 7.7PHV4 데스크톱/일체형",
                "category":"통합 드라이버 설치 프로그램",
                "date":"20190104",
                "url":"https://www.lgservice.co.kr/fileExDownload.do?filePath=/data001/GSCS/FILE/P1/file/2018/01/2018-01-24&fileName=c0a8ed6e03324c96887cf6a649fbb020.pdf&fileRealName=MFL67233150_171127.pdf&check=true",
                "fileSize":"118.1MB",
                "list":null
            }
        ]
    }
}