{
    "status": true,
    "message":null,
    "data": {
        "solutionsList":[
            {
                "title": "노인복지시설에 재능 기부 펼친 LG전자서비스 경남팀노인복지시설에 재능 기부 펼친 LG전자서비스 경남팀노인복지시설에 재능 기부 펼친 LG전자서비스 경남팀노인복지시설에 재능 기부 펼친 LG전자서비스 경남팀노인복지시설에 재능 기부 펼친 LG전자서비스 경남팀",
                "topic": "증상 > 세부 증상",
                "date": "2020.02.27",
                "view": "5,692",
                "video": true
            },
            {
                "title": "노인복지시설에 재능 기부 펼친 LG전자서비스 경남팀2",
                "topic": "증상 > 세부 증상",
                "date": "2020.02.27",
                "view": "5,692"
            },
            {
                "title": "노인복지시설에 재능 기부 펼친 LG전자서비스 경남팀3",
                "topic": "증상 > 세부 증상",
                "date": "2020.02.27",
                "view": "5,692"
            },
            {
                "title": "노인복지시설에 재능 기부 펼친 LG전자서비스 경남팀4",
                "topic": "증상 > 세부 증상",
                "date": "2020.02.27",
                "view": "5,692"
            },
            {
                "title": "노인복지시설에 재능 기부 펼친 LG전자서비스 경남팀5",
                "topic": "증상 > 세부 증상",
                "date": "2020.02.27",
                "view": "5,692"
            },
            {
                "title": "노인복지시설에 재능 기부 펼친 LG전자서비스 경남팀6",
                "topic": "증상 > 세부 증상",
                "date": "2020.02.27",
                "view": "5,692"
            },
            {
                "title": "노인복지시설에 재능 기부 펼친 LG전자서비스 경남팀7",
                "topic": "증상 > 세부 증상",
                "date": "2020.02.27",
                "view": "5,692"
            },
            {
                "title": "노인복지시설에 재능 기부 펼친 LG전자서비스 경남팀8",
                "topic": "증상 > 세부 증상",
                "date": "2020.02.27",
                "view": "5,692"
            },
            {
                "title": "노인복지시설에 재능 기부 펼친 LG전자서비스 경남팀9",
                "topic": "증상 > 세부 증상",
                "date": "2020.02.27",
                "view": "5,692"
            },
            {
                "title": "노인복지시설에 재능 기부 펼친 LG전자서비스 경남팀10",
                "topic": "증상 > 세부 증상",
                "date": "2020.02.27",
                "view": "5,692"
            }
        ],
        "pageInfo":{
            "page":2,
            "startPage":1,
            "endPage":5,
            "totalCount":59,
            "prevBtn":false,
            "nextBtn":true
        }
    }
}